chunklog/__about__.py
chunklog/__main__.py
chunklog/browser_output.py
chunklog/cache.py
chunklog/colored_output.py
chunklog/entry.py
chunklog/webserver.py
chunklog-0.5.dist-info/METADATA
chunklog-0.5.dist-info/WHEEL
chunklog-0.5.dist-info/licenses/LICENSE
chunklog-0.5.dist-info/RECORD
