Metadata-Version: 2.1
Name: chunklog
Version: 0.5
Project-URL: Documentation, https://gitlab.com/treqs-on-git/chunklog#readme
Project-URL: Issues, https://gitlab.com/treqs-on-git/chunklog/issues
Project-URL: Source, https://gitlab.com/treqs-on-git/chunklog
Author-email: noraojensa <ojensa@student.chalmers.se>, audurkatarina <audurkatarina@live.com>
Maintainer-email: Nora Ojensa <ojensa@student.chalmers.se>, Audur Katarina Theodorsdottir <audurkatarina@live.com>, Filip Lange <filip.lange@gmail.com>, Eric Knauss <eric.knauss@cse.gu.se>
License-File: LICENSE
Classifier: Development Status :: 4 - Beta
Classifier: Programming Language :: Python
Classifier: Programming Language :: Python :: 3.7
Classifier: Programming Language :: Python :: 3.8
Classifier: Programming Language :: Python :: 3.9
Classifier: Programming Language :: Python :: 3.10
Classifier: Programming Language :: Python :: 3.11
Classifier: Programming Language :: Python :: Implementation :: CPython
Classifier: Programming Language :: Python :: Implementation :: PyPy
Requires-Python: >=3.7
Requires-Dist: gitpython
Requires-Dist: more-itertools
Requires-Dist: pytest-mock
Requires-Dist: rich
Requires-Dist: typer
